{
    "id": 70,
    "title": "#67 -았/었/했으면 좋겠다 (希望...)",
    "part": 18,
    "introDialogue": {
        "A": "생일에 무엇을 받고 싶어요?",
        "A_zh": "生日想收到什麼？",
        "B": "친구가 선물을 줬으면 좋겠어요.",
        "B_zh": "希望朋友能送我禮物。",
        "vocabBreakdown": [
            {
                "ko": "생일",
                "zh": "生日"
            },
            {
                "ko": "받다",
                "zh": "收到"
            },
            {
                "ko": "선물",
                "zh": "禮物"
            }
        ]
    },
    "grammarRule": {
        "explanation": "表示說話者的願望、希望或期待發生的事情。",
        "note": "雖然使用了過去式標記，但表示的是對未來或現狀的希望。",
        "detailedInstruction": [
            "1. 結構：詞幹 + 았/었/했으면 좋겠다。",
            "2. 變形：與過去式相同。ㅏ, ㅗ 接 았으면；其餘接 었으면；하다 變為 했으면。",
            "3. 語意：『要是...的話就好了』。語氣比『-고 싶다』更強調對某種狀態的期待。",
            "4. 應用：可以用於希望天氣好、希望某人來等情況。"
        ]
    },
    "examples": [
        {
            "ko": "내일 날씨가 좋았으면 좋겠어요.",
            "zh": "希望明天天氣好。"
        },
        {
            "ko": "돈이 많았으면 좋겠어요.",
            "zh": "希望錢很多。"
        },
        {
            "ko": "시험이 쉬웠으면 좋겠어요.",
            "zh": "希望考試簡單一點。"
        },
        {
            "ko": "빨리 한국에 갔으면 좋겠어요.",
            "zh": "希望快點去韓國。"
        },
        {
            "ko": "A: 방학에 무엇을 하고 싶어요? \nB: 여행을 갔으면 좋겠어요.",
            "zh": "A: 放假想做什麼？\nB: 希望能去旅行。"
        },
        {
            "ko": "A: 배가 고파요? \nB: 네, 빨리 밥을 먹었으면 좋겠어요.",
            "zh": "A: 肚子餓嗎？\nB: 是的，希望快點吃飯。"
        }
    ],
    "relatedVocabIds": [
        "V1179",
        "V1180",
        "V1181",
        "V1182",
        "V1183",
        "V1184",
        "V1185",
        "V1186",
        "V1187",
        "V1188",
        "V1189",
        "V1190",
        "V1191",
        "V1192",
        "V1193",
        "V1194",
        "V1195",
        "V1196",
        "V1197"
    ]
}